orbis_addon_tunnelblick/__init__.py
orbis_addon_tunnelblick/description.txt
orbis_addon_tunnelblick/html_pages.py
orbis_addon_tunnelblick/html_templates.py
orbis_addon_tunnelblick/main.py
orbis_addon_tunnelblick-2.1.1.dist-info/LICENSE
orbis_addon_tunnelblick-2.1.1.dist-info/METADATA
orbis_addon_tunnelblick-2.1.1.dist-info/WHEEL
orbis_addon_tunnelblick-2.1.1.dist-info/top_level.txt
orbis_addon_tunnelblick-2.1.1.dist-info/RECORD
