Metadata-Version: 2.1
Name: orbis-addon-tunnelblick
Version: 2.1.1
Summary: The Tunnelblick Addon for Orbis view gold standards.
Home-page: https://github.com/orbis-eval/orbis_addon_tunnelblick
Author: fabod
License: GPL2
Platform: UNKNOWN
Requires-Python: >3.6
Requires-Dist: palettable (==3.1.1)
